Metadata-Version: 1.0
Name: infinity4py
Version: 0.0.1
Summary: infinity for python
Home-page: https://github.com/NatriumLab/infinity4py
Author: Chenwe-i-lin
Author-email: 1846913566@qq.com
License: MIT
Platform: UNKNOWN
